litedfs_client/__init__.py
litedfs_client/client.py
litedfs_client/logger.py
litedfs_client/version.py
litedfs_client-0.0.12.dist-info/METADATA
litedfs_client-0.0.12.dist-info/WHEEL
litedfs_client-0.0.12.dist-info/top_level.txt
litedfs_client-0.0.12.dist-info/RECORD
