Metadata-Version: 2.1
Name: litedfs-client
Version: 0.0.12
Summary: LiteDFS Client: distributed file system python client
Home-page: https://github.com/fiefdx/LiteDFS
Author: fiefdx
Author-email: fiefdx@163.com
License: MIT
Platform: UNKNOWN
Classifier: License :: OSI Approved :: MIT License
Classifier: Programming Language :: Python :: 3
Classifier: Programming Language :: Python :: 3.7
Requires-Dist: requests (>=2.22.0)
Requires-Dist: tea-encrypt
